[
  {
    "id": 202,
    "introduction": "",
    "sections": [
      {
        "title": "",
        "introduction": "",
        "paragraphs": [
          {
            "title": "God Explains Judgment",
            "references": [
              {
                "book": "Isaiah",
                "chapter": 65,
                "verse": "1-7"
              }
            ]
          },
          {
            "title": "Salvation of Remnant",
            "references": [
              {
                "book": "Isaiah",
                "chapter": 65,
                "verse": "8-10"
              }
            ]
          },
          {
            "title": "No Mercy for Unrepentant",
            "references": [
              {
                "book": "Isaiah",
                "chapter": 65,
                "verse": "11-12"
              }
            ]
          },
          {
            "title": "Blessings for Servants",
            "references": [
              {
                "book": "Isaiah",
                "chapter": 65,
                "verse": "13-16"
              }
            ]
          },
          {
            "title": "New Heavens and a New Earth",
            "references": [
              {
                "book": "Isaiah",
                "chapter": 65,
                "verse": "17-25"
              }
            ]
          },
          {
            "title": "God's Majesty and Power",
            "references": [
              {
                "book": "Isaiah",
                "chapter": 66,
                "verse": "1-2"
              }
            ]
          },
          {
            "title": "God's Enemies Will Fall",
            "references": [
              {
                "book": "Isaiah",
                "chapter": 66,
                "verse": "3-6"
              }
            ]
          },
          {
            "title": "Believers Will Be Rewarded",
            "references": [
              {
                "book": "Isaiah",
                "chapter": 66,
                "verse": "7-14"
              }
            ]
          },
          {
            "title": "Destruction of the Wicked",
            "references": [
              {
                "book": "Isaiah",
                "chapter": 66,
                "verse": "15-17"
              }
            ]
          },
          {
            "title": "Survivors to Be Evangelists",
            "references": [
              {
                "book": "Isaiah",
                "chapter": 66,
                "verse": "18-21"
              }
            ]
          },
          {
            "title": "Eternal Life and Death",
            "references": [
              {
                "book": "Isaiah",
                "chapter": 66,
                "verse": "22-24"
              }
            ]
          }
        ]
      },
      {
        "introduction": "How anyone could ignore or reject such a powerful message is difficult to fathom. But Isaiah himself speaks of those who will refuse to hear or see. Some will reject the message because they are willfully stubborn, and others because they are caught up in material pursuits, or pleasurable diversions, or even false religious worship. Perhaps saddest of all, God's message will sometimes be hidden from the common people by the very ones who ought to bring understanding—the religious leaders. Once again Isaiah singles out these leaders for special judgment. It is quite possible that this very condemnation proves to be the death knell for Isaiah, for tradition holds that Isaiah was sawn in two by his enemies during Manasseh's reign."
      },
      {
        "title": "Spiritual Renewal Under Manasseh",
        "introduction": "As a result of his wicked leadership, Manasseh is taken captive to Babylon by the army of a now-eclipsing Assyrian empire. There in exile with many of his fellow countrymen, Manasseh is conscience-stricken and sincerely repents. Consequently, God reestablishes Manasseh on the throne in Judah, and Manasseh does what he can do abolish the very idolatry he introduced. The historical record begins with a note about the Assyrian coup in which Sennacherib is assassinated by his own sons."
      },
      {
        "title": "",
        "paragraphs": [
          {
            "title": "Sennacherib Assassinated",
            "references": [
              {
                "book": "2 Kings",
                "chapter": 19,
                "verse": "37"
              },
              {
                "book": "Isaiah",
                "chapter": 37,
                "verse": "38"
              }
            ]
          },
          {
            "title": "Manasseh Taken Captive",
            "references": [
              {
                "book": "2 Chronicles",
                "chapter": 33,
                "verse": "10-11"
              }
            ]
          },
          {
            "title": "Repentance Brings Restoration",
            "references": [
              {
                "book": "2 Chronicles",
                "chapter": 33,
                "verse": "12-13"
              }
            ]
          },
          {
            "title": "Manasseh Reforms Judah",
            "references": [
              {
                "book": "2 Chronicles",
                "chapter": 33,
                "verse": "14-17"
              }
            ]
          }
        ]
      }
    ]
  }
]
